trejas_enlitic/__init__.py
trejas_enlitic/functions.py
trejas_enlitic/cli/__init__.py
trejas_enlitic/utils/__init__.py
trejas_enlitic/utils/log/__init__.py
trejas_enlitic/utils/log/logging_mixin.py
trejas_enlitic-0.0.2.dist-info/METADATA
trejas_enlitic-0.0.2.dist-info/WHEEL
trejas_enlitic-0.0.2.dist-info/entry_points.txt
trejas_enlitic-0.0.2.dist-info/top_level.txt
trejas_enlitic-0.0.2.dist-info/RECORD
