Metadata-Version: 2.1
Name: trejas-enlitic
Version: 0.0.2
Summary: Funcitons to report on logs.
Home-page: UNKNOWN
Author: Traey Hatch
Author-email: traeyhatch@gmail.com
License: UNKNOWN
Platform: UNKNOWN
Requires-Dist: click (==7.1.2)
Requires-Dist: colorlog (==4.2.1)
Requires-Dist: pandas (==1.1.3)
Requires-Dist: tabulate (==0.8.7)
